ambition_export/__init__.py
ambition_export/admin_site.py
ambition_export/apps.py
ambition_export/column_handlers.py
ambition_export/df_handlers.py
ambition_export/system_checks.py
ambition_export/urls.py
ambition_export/wsgi.py
ambition_export/tests/__init__.py
ambition_export/tests/test_export.py
ambition_export-0.1.10.dist-info/AUTHORS
ambition_export-0.1.10.dist-info/LICENSE
ambition_export-0.1.10.dist-info/METADATA
ambition_export-0.1.10.dist-info/WHEEL
ambition_export-0.1.10.dist-info/top_level.txt
ambition_export-0.1.10.dist-info/RECORD
